task_mcmc/__init__.py
task_mcmc/runMCMC.py
task_mcmc/thabo_and_zach_work.py
task_mcmc-1.0.1.dist-info/DESCRIPTION.rst
task_mcmc-1.0.1.dist-info/METADATA
task_mcmc-1.0.1.dist-info/RECORD
task_mcmc-1.0.1.dist-info/WHEEL
task_mcmc-1.0.1.dist-info/entry_points.txt
task_mcmc-1.0.1.dist-info/metadata.json
task_mcmc-1.0.1.dist-info/top_level.txt
